LICENSE
README.md
setup.py
BCAWT/ATCG3.py
BCAWT/BCAWT.py
BCAWT/BCAWT_auto_test.py
BCAWT/CA.py
BCAWT/CA_RSCU.py
BCAWT/ENc.py
BCAWT/GC123.py
BCAWT/GRAVY_AROMO.py
BCAWT/Optimal_codon_corr_method.py
BCAWT/P2_index.py
BCAWT/PR2_plot_data.py
BCAWT/__init__.py
BCAWT.egg-info/PKG-INFO
BCAWT.egg-info/SOURCES.txt
BCAWT.egg-info/dependency_links.txt
BCAWT.egg-info/requires.txt
BCAWT.egg-info/top_level.txt