Metadata-Version: 2.1
Name: BCAWT
Version: 1.0.6
Summary: Manages a complete workflow to analysis the codon usage bias
Home-page: https://github.com/AliYoussef96/BCAW-Tool
Author: Ali Mostafa Anwar
Author-email: aliali.mostafa99@gmail.com
License: MIT
Platform: UNKNOWN
Classifier: License :: OSI Approved :: MIT License
Classifier: Programming Language :: Python :: 3
Classifier: Intended Audience :: Science/Research
Classifier: Topic :: Scientific/Engineering :: Bio-Informatics
Requires-Python: >=3.7.0
License-File: LICENSE
